distutils_twine/__init__.py
distutils_twine-3.0.0.dist-info/METADATA
distutils_twine-3.0.0.dist-info/RECORD
distutils_twine-3.0.0.dist-info/WHEEL
distutils_twine-3.0.0.dist-info/top_level.txt
