Metadata-Version: 2.1
Name: distutils-twine
Version: 3.0.0
Summary: Use Twine to make a setup.py release command.
Home-page: https://github.com/duckinator/distutils_twine
Author: Ellen Marie Dash
Author-email: me@duckie.co
License: MIT
Platform: UNKNOWN
Classifier: Programming Language :: Python :: 3
Classifier: License :: OSI Approved :: MIT License
Classifier: Operating System :: OS Independent
Requires-Python: ~=3.6
